moose/__init__.py
moose/_moose.cpython-38-x86_64-linux-gnu.so
moose/constants.py
moose/fixXreacs.py
moose/hdfutil.py
moose/helper.py
moose/methods_utils.py
moose/model_utils.py
moose/moose_constants.py
moose/moose_legacy.py
moose/network_utils.py
moose/plot_utils.py
moose/print_utils.py
moose/recording.py
moose/server.py
moose/streamer_utils.py
moose/tests.py
moose/utils.py
moose/chemUtil/rainbow2.pkl
moose/neuroml2/schema/NeuroMLCoreDimensions.xml
rdesigneur/__init__.py
rdesigneur/moogul.py
rdesigneur/rdesigneur.py
rdesigneur/rdesigneurProtos.py
rdesigneur/rmoogli.py
pymoose_community-3.4.0.dev20220115.dist-info/METADATA
pymoose_community-3.4.0.dev20220115.dist-info/WHEEL
pymoose_community-3.4.0.dev20220115.dist-info/top_level.txt
pymoose_community-3.4.0.dev20220115.dist-info/RECORD
