Metadata-Version: 2.1
Name: pymoose-community
Version: 3.4.0.dev20220115
Summary: Fork of Python scripting interface of MOOSE Simulator (https://moose.ncbs.res.in)
Home-page: http://moose.ncbs.res.in
Author: MOOSERes
Author-email: bhalla@ncbs.res.in
Maintainer: Dilawar Singh
Maintainer-email: dilawars@ncbs.res.in
License: UNKNOWN
Platform: UNKNOWN
Requires-Dist: numpy
Requires-Dist: matplotlib
